lite_cache/LiteCache.py
lite_cache/__init__.py
lite_cache-0.1.3.dist-info/LICENSE
lite_cache-0.1.3.dist-info/METADATA
lite_cache-0.1.3.dist-info/WHEEL
lite_cache-0.1.3.dist-info/top_level.txt
lite_cache-0.1.3.dist-info/RECORD
